{"classes":["ASSASSIN"],"cost_memory":null,"cost_reserve":3,"created_at":"2025-03-04T21:56:32.906Z","durability":null,"editions":[{"card_id":"09axbotwlz","collector_number":"147","configuration":"default","created_at":"2025-03-04T21:56:32.906+00:00","effect":null,"effect_raw":null,"flavor":"Victory lies not only in the clash of weapons, but in the unseen currents that steer the flow of fate.","illustrator":"Hanh Chu","image":"/cards/images/zhang-he-cloak-of-night-hvn.jpg","last_update":"2025-03-04T21:56:32.906+00:00","orientation":null,"rarity":4,"slug":"zhang-he-cloak-of-night-hvn","thema_charm_foil":257,"thema_charm_nonfoil":48,"thema_ferocity_foil":260,"thema_ferocity_nonfoil":49,"thema_foil":1246,"thema_grace_foil":241,"thema_grace_nonfoil":45,"thema_mystique_foil":268,"thema_mystique_nonfoil":50,"thema_nonfoil":233,"thema_valor_foil":220,"thema_valor_nonfoil":41,"uuid":"fmpi8dpoxb","collaborators":[],"circulationTemplates":[{"created_at":"2025-03-04T21:56:32.906+00:00","edition_id":"fmpi8dpoxb","foil":true,"kind":"FOIL","last_update":"2025-03-04T21:56:32.906+00:00","name":"HVN Super Rare Foil","population":610,"population_operator":"≈","printing":true,"uuid":"MLJXC0JgaR","variants":[]},{"created_at":"2025-03-04T21:56:32.906+00:00","edition_id":"fmpi8dpoxb","foil":false,"kind":"NONFOIL","last_update":"2025-03-04T21:56:32.906+00:00","name":"HVN Super Rare","population":13500,"population_operator":"≈","printing":true,"uuid":"seMr6VRxxb","variants":[]}],"circulations":[],"other_orientations":[],"set":{"created_at":"2025-03-04T21:56:32.906+00:00","id":"67uvnnrprp","language":"EN","last_update":"2025-03-04T21:56:32.906+00:00","name":"Abyssal Heaven","prefix":"HVN","release_date":"2025-03-07T00:00:00"},"effect_html":null}],"effect":"[Class Bonus] **On Enter**: Another target ally you control gains **stealth** for as long as you control Zhang He.","effect_raw":"[Class Bonus] On Enter: Another target ally you control gains stealth for as long as you control Zhang He.","element":"WATER","elements":["WATER"],"flavor":null,"last_update":"2025-03-07T16:36:57.052Z","legality":null,"level":null,"life":2,"name":"Zhang He, Cloak of Night","power":2,"referenced_by":[],"references":[],"result_editions":[{"card_id":"09axbotwlz","collector_number":"147","configuration":"default","created_at":"2025-03-04T21:56:32.906+00:00","effect":null,"effect_raw":null,"flavor":"Victory lies not only in the clash of weapons, but in the unseen currents that steer the flow of fate.","illustrator":"Hanh Chu","image":"/cards/images/zhang-he-cloak-of-night-hvn.jpg","last_update":"2025-03-04T21:56:32.906+00:00","orientation":null,"rarity":4,"slug":"zhang-he-cloak-of-night-hvn","thema_charm_foil":257,"thema_charm_nonfoil":48,"thema_ferocity_foil":260,"thema_ferocity_nonfoil":49,"thema_foil":1246,"thema_grace_foil":241,"thema_grace_nonfoil":45,"thema_mystique_foil":268,"thema_mystique_nonfoil":50,"thema_nonfoil":233,"thema_valor_foil":220,"thema_valor_nonfoil":41,"uuid":"fmpi8dpoxb","collaborators":[],"circulationTemplates":[{"created_at":"2025-03-04T21:56:32.906+00:00","edition_id":"fmpi8dpoxb","foil":true,"kind":"FOIL","last_update":"2025-03-04T21:56:32.906+00:00","name":"HVN Super Rare Foil","population":610,"population_operator":"≈","printing":true,"uuid":"MLJXC0JgaR","variants":[]},{"created_at":"2025-03-04T21:56:32.906+00:00","edition_id":"fmpi8dpoxb","foil":false,"kind":"NONFOIL","last_update":"2025-03-04T21:56:32.906+00:00","name":"HVN Super Rare","population":13500,"population_operator":"≈","printing":true,"uuid":"seMr6VRxxb","variants":[]}],"circulations":[],"other_orientations":[],"set":{"created_at":"2025-03-04T21:56:32.906+00:00","id":"67uvnnrprp","language":"EN","last_update":"2025-03-04T21:56:32.906+00:00","name":"Abyssal Heaven","prefix":"HVN","release_date":"2025-03-07T00:00:00"},"effect_html":null}],"rule":[],"slug":"zhang-he-cloak-of-night","speed":null,"subtypes":["ASSASSIN","HUMAN"],"types":["UNIQUE","ALLY"],"uuid":"09axbotwlz","effect_html":"<span class=\"effect__bubble\">Class Bonus</span>  <span class=\"effect__label\">On Enter</span>: Another target ally you control gains <span class=\"effect__label\">stealth</span> for as long as you control Zhang He."}