{"uuid":"1BkfdFqCrG","types":["ACTION"],"classes":["CLERIC"],"subtypes":["CLERIC","SPELL"],"element":"WATER","name":"Revitalizing Cleanse","slug":"revitalizing-cleanse","effect":"Reveal all cards in your memory. <span class=\"effect__label\">Recover X</span> where <span class=\"effect__label\">X</span> is the amount of water element cards revealed this way. Draw a card. <span class=\"effect__reminder\">(To <span class=\"effect__label\">recover</span>, remove that many damage counters from your champion.)</span>","effect_raw":"Reveal all cards in your memory. Recover X where X is the amount of water element cards revealed this way. Draw a card. (To recover, remove that many damage counters from your champion.)","rule":null,"flavor":"A healing prayer for the pure of soul.","cost_memory":null,"cost_reserve":5,"level":null,"power":null,"life":null,"durability":null,"speed":true,"legality":null,"related_ids":null,"last_update":"2022-12-26T06:00:00.000Z","result_editions":[{"uuid":"xnin8hgsuw","card_id":"1BkfdFqCrG","collector_number":"186","slug":"revitalizing-cleanse-doa-alter","illustrator":"道漫","rarity":1,"effect":null,"flavor":null,"thema_grace_nonfoil":13,"thema_valor_nonfoil":12,"thema_charm_nonfoil":15,"thema_mystique_nonfoil":17,"thema_ferocity_nonfoil":8,"thema_grace_foil":149,"thema_valor_foil":137,"thema_charm_foil":171,"thema_mystique_foil":194,"thema_ferocity_foil":93,"thema_foil":744,"thema_nonfoil":65,"circulations":[],"circulationTemplates":[{"uuid":"vlgl6ffqsu","name":"DOA-Alter 1 C Foils","foil":true,"printing":true,"population_operator":"≈","population":624},{"uuid":"8lzc81mtts","name":"DOA-Alter 1 C NF","foil":false,"printing":true,"population_operator":"≈","population":66404}],"set":{"name":"Dawn of Ashes Alter Edition","prefix":"DOA Alter","language":"EN"}}],"editions":[{"uuid":"xnin8hgsuw","card_id":"1BkfdFqCrG","collector_number":"186","slug":"revitalizing-cleanse-doa-alter","illustrator":"道漫","rarity":1,"effect":null,"flavor":null,"last_update":"2023-04-15T06:00:00.000Z","thema_grace_nonfoil":13,"thema_valor_nonfoil":12,"thema_charm_nonfoil":15,"thema_mystique_nonfoil":17,"thema_ferocity_nonfoil":8,"thema_grace_foil":149,"thema_valor_foil":137,"thema_charm_foil":171,"thema_mystique_foil":194,"thema_ferocity_foil":93,"thema_foil":744,"thema_nonfoil":65,"circulations":[],"circulationTemplates":[{"uuid":"vlgl6ffqsu","name":"DOA-Alter 1 C Foils","foil":true,"printing":true,"population_operator":"≈","population":624},{"uuid":"8lzc81mtts","name":"DOA-Alter 1 C NF","foil":false,"printing":true,"population_operator":"≈","population":66404}],"set":{"name":"Dawn of Ashes Alter Edition","prefix":"DOA Alter","language":"EN","last_update":"2023-04-15T06:00:00.000Z"}},{"uuid":"uciVVe1Lzv","card_id":"1BkfdFqCrG","collector_number":"186","slug":"revitalizing-cleanse-doa1e","illustrator":"道漫","rarity":1,"effect":null,"flavor":null,"last_update":"2022-12-26T06:00:00.000Z","thema_grace_nonfoil":14,"thema_valor_nonfoil":13,"thema_charm_nonfoil":16,"thema_mystique_nonfoil":18,"thema_ferocity_nonfoil":9,"thema_grace_foil":160,"thema_valor_foil":149,"thema_charm_foil":182,"thema_mystique_foil":206,"thema_ferocity_foil":103,"thema_foil":800,"thema_nonfoil":70,"circulations":[],"circulationTemplates":[{"uuid":"y7nkIL2Scb","name":"DOA1e Foils 1","foil":true,"printing":false,"population_operator":"≈","population":157},{"uuid":"1Y3QQXxc35","name":"DOA1e Commons NF","foil":false,"printing":false,"population_operator":"≈","population":24000}],"set":{"name":"Dawn of Ashes First Edition","prefix":"DOA 1st","language":"EN","last_update":"2022-12-28T06:00:00.000Z"}},{"uuid":"pvwuyejo9i","card_id":"1BkfdFqCrG","collector_number":"083","slug":"revitalizing-cleanse-doasd","illustrator":"道漫","rarity":1,"effect":null,"flavor":null,"last_update":"2023-04-15T06:00:00.000Z","thema_grace_nonfoil":12,"thema_valor_nonfoil":11,"thema_charm_nonfoil":14,"thema_mystique_nonfoil":16,"thema_ferocity_nonfoil":9,"thema_grace_foil":null,"thema_valor_foil":null,"thema_charm_foil":null,"thema_mystique_foil":null,"thema_ferocity_foil":null,"thema_foil":null,"thema_nonfoil":62,"circulations":[],"circulationTemplates":[{"uuid":"x58ixy4b7s","name":"DOASD 3","foil":null,"printing":true,"population_operator":"≈","population":45000}],"set":{"name":"Dawn of Ashes Starter Decks","prefix":"DOASD","language":"EN","last_update":"2023-04-15T06:00:00.000Z"}}]}