{"classes":["CLERIC"],"cost_memory":null,"cost_reserve":2,"created_at":"2025-03-04T21:56:32.906Z","durability":null,"editions":[{"card_id":"1k2jb8mau1","collector_number":"063","configuration":"default","created_at":"2025-03-04T21:56:32.906+00:00","effect":null,"effect_raw":null,"flavor":null,"illustrator":"Dragonart","image":"/cards/images/shimmering-refraction-hvn.jpg","last_update":"2025-03-04T21:56:32.906+00:00","orientation":null,"rarity":2,"slug":"shimmering-refraction-hvn","thema_charm_foil":181,"thema_charm_nonfoil":23,"thema_ferocity_foil":208,"thema_ferocity_nonfoil":26,"thema_foil":893,"thema_grace_foil":192,"thema_grace_nonfoil":24,"thema_mystique_foil":176,"thema_mystique_nonfoil":22,"thema_nonfoil":112,"thema_valor_foil":136,"thema_valor_nonfoil":17,"uuid":"4e5l418snu","collaborators":[],"circulationTemplates":[{"created_at":"2025-03-04T21:56:32.906+00:00","edition_id":"4e5l418snu","foil":true,"kind":"FOIL","last_update":"2025-03-04T21:56:32.906+00:00","name":"HVN Uncommon Foil","population":1400,"population_operator":"≈","printing":true,"uuid":"EliEet0e4Q","variants":[]},{"created_at":"2025-03-04T21:56:32.906+00:00","edition_id":"4e5l418snu","foil":false,"kind":"NONFOIL","last_update":"2025-03-04T21:56:32.906+00:00","name":"HVN Uncommon","population":66500,"population_operator":"≈","printing":true,"uuid":"dzQX5gJD7Z","variants":[]}],"circulations":[],"other_orientations":[],"set":{"created_at":"2025-03-04T21:56:32.906+00:00","id":"67uvnnrprp","language":"EN","last_update":"2025-03-04T21:56:32.906+00:00","name":"Abyssal Heaven","prefix":"HVN","release_date":"2025-03-07T00:00:00"},"effect_html":null},{"card_id":"1k2jb8mau1","collector_number":"015","configuration":"default","created_at":"2025-03-04T21:56:32.906+00:00","effect":null,"effect_raw":null,"flavor":null,"illustrator":"Dragonart","image":"/cards/images/shimmering-refraction-rec-idy.jpg","last_update":"2025-03-04T21:56:32.906+00:00","orientation":null,"rarity":2,"slug":"shimmering-refraction-rec-idy","thema_charm_foil":null,"thema_charm_nonfoil":11,"thema_ferocity_foil":null,"thema_ferocity_nonfoil":9,"thema_foil":null,"thema_grace_foil":null,"thema_grace_nonfoil":13,"thema_mystique_foil":null,"thema_mystique_nonfoil":15,"thema_nonfoil":65,"thema_valor_foil":null,"thema_valor_nonfoil":17,"uuid":"xbtdpjlisf","collaborators":[],"circulationTemplates":[{"created_at":"2025-03-04T21:56:32.906+00:00","edition_id":"xbtdpjlisf","foil":false,"kind":"NONFOIL","last_update":"2025-03-06T02:56:32.906+00:00","name":"HVN ReC x4","population":72000,"population_operator":"≈","printing":true,"uuid":"LC6ILexjna","variants":[]}],"circulations":[],"other_orientations":[],"set":{"created_at":"2025-03-04T21:56:32.906+00:00","id":"f1bxvdbqfu","language":"EN","last_update":"2025-03-04T21:56:32.906+00:00","name":"Re:Collection Idyll Corsage","prefix":"ReC-IDY","release_date":"2025-03-07T00:00:00"},"effect_html":null}],"effect":"Deal **X** damage to target unit, where **X** is the amount of phantasias you control. \n\n[Diao Chan Bonus] If Shimmering Refraction was activated from your memory, draw a card into your memory.","effect_raw":"Deal X damage to target unit, where X is the amount of phantasias you control. \n\n[Diao Chan Bonus] If Shimmering Refraction was activated from your memory, draw a card into your memory.","element":"NORM","flavor":null,"last_update":"2025-03-07T16:36:57.052Z","legality":null,"level":null,"life":null,"name":"Shimmering Refraction","power":null,"referenced_by":[],"references":[],"result_editions":[{"card_id":"1k2jb8mau1","collector_number":"015","configuration":"default","created_at":"2025-03-04T21:56:32.906+00:00","effect":null,"effect_raw":null,"flavor":null,"illustrator":"Dragonart","image":"/cards/images/shimmering-refraction-rec-idy.jpg","last_update":"2025-03-04T21:56:32.906+00:00","orientation":null,"rarity":2,"slug":"shimmering-refraction-rec-idy","thema_charm_foil":null,"thema_charm_nonfoil":11,"thema_ferocity_foil":null,"thema_ferocity_nonfoil":9,"thema_foil":null,"thema_grace_foil":null,"thema_grace_nonfoil":13,"thema_mystique_foil":null,"thema_mystique_nonfoil":15,"thema_nonfoil":65,"thema_valor_foil":null,"thema_valor_nonfoil":17,"uuid":"xbtdpjlisf","collaborators":[],"circulationTemplates":[{"created_at":"2025-03-04T21:56:32.906+00:00","edition_id":"xbtdpjlisf","foil":false,"kind":"NONFOIL","last_update":"2025-03-06T02:56:32.906+00:00","name":"HVN ReC x4","population":72000,"population_operator":"≈","printing":true,"uuid":"LC6ILexjna","variants":[]}],"circulations":[],"other_orientations":[],"set":{"created_at":"2025-03-04T21:56:32.906+00:00","id":"f1bxvdbqfu","language":"EN","last_update":"2025-03-04T21:56:32.906+00:00","name":"Re:Collection Idyll Corsage","prefix":"ReC-IDY","release_date":"2025-03-07T00:00:00"},"effect_html":null}],"rule":[],"slug":"shimmering-refraction","speed":true,"subtypes":["CLERIC","SPELL","REACTION"],"types":["ACTION"],"uuid":"1k2jb8mau1","effect_html":"<span class=\"effect__block\">Deal <span class=\"effect__label\">X</span> damage to target unit, where <span class=\"effect__label\">X</span> is the amount of phantasias you control. </span><span class=\"effect__bubble\">Diao Chan Bonus</span>  If Shimmering Refraction was activated from your memory, draw a card into your memory."}