{"classes":["GUARDIAN"],"cost_memory":null,"cost_reserve":8,"created_at":"2025-05-27T20:27:36.974Z","durability":null,"editions":[{"card_id":"CzwVavXMQU","collector_number":"198","configuration":"default","created_at":"2025-05-27T20:27:36.974+00:00","effect":null,"effect_raw":null,"flavor":null,"illustrator":"Primea Studio","image":"/cards/images/dorumegian-foundry-mrc-alter.jpg","last_update":"2025-05-27T20:27:36.974+00:00","orientation":null,"rarity":2,"slug":"dorumegian-foundry-mrc-alter","thema_charm_foil":120,"thema_charm_nonfoil":15,"thema_ferocity_foil":177,"thema_ferocity_nonfoil":22,"thema_foil":826,"thema_grace_foil":152,"thema_grace_nonfoil":19,"thema_mystique_foil":225,"thema_mystique_nonfoil":28,"thema_nonfoil":103,"thema_valor_foil":152,"thema_valor_nonfoil":19,"uuid":"e2Rsg9X1o9","collaborators":[],"circulationTemplates":[{"created_at":"2025-05-27T20:27:36.974+00:00","edition_id":"e2Rsg9X1o9","foil":true,"kind":"FOIL","last_update":"2025-05-27T20:27:36.974+00:00","name":"MRCA U Foil","population":550,"population_operator":"≈","printing":true,"uuid":"cAUDvMk4HC","variants":[]},{"created_at":"2025-05-27T20:27:36.974+00:00","edition_id":"e2Rsg9X1o9","foil":false,"kind":"NONFOIL","last_update":"2025-05-27T20:27:36.974+00:00","name":"MRCA U","population":54200,"population_operator":"≈","printing":true,"uuid":"e7FEx0Jzyn","variants":[]}],"circulations":[],"other_orientations":[],"set":{"created_at":"2025-05-27T20:27:36.974+00:00","id":"a8950b3290","language":"EN","last_update":"2025-05-27T20:27:36.974+00:00","name":"Mercurial Heart Alter Edition","prefix":"MRC Alter","release_date":"2025-05-30T00:00:00"},"effect_html":null}],"effect":"[Class Bonus] This card costs 2 less to activate for each of up to three domains you control.\n\n**On Enter:** **Summon** an Automaton Drone token with a **buff** counter on it.","effect_raw":"[Class Bonus] This card costs 2 less to activate for each of up to three domains you control.\n\nOn Enter: Summon an Automaton Drone token with a buff counter on it.","element":"NORM","elements":["NORM"],"flavor":"A city cannot be built in a day, but a machine can.","last_update":"2025-05-27T20:27:36.974Z","legality":null,"level":null,"life":null,"name":"Dorumegian Foundry","power":null,"referenced_by":[],"references":[],"result_editions":[{"card_id":"CzwVavXMQU","collector_number":"198","configuration":"default","created_at":"2025-05-27T20:27:36.974+00:00","effect":null,"effect_raw":null,"flavor":null,"illustrator":"Primea Studio","image":"/cards/images/dorumegian-foundry-mrc-alter.jpg","last_update":"2025-05-27T20:27:36.974+00:00","orientation":null,"rarity":2,"slug":"dorumegian-foundry-mrc-alter","thema_charm_foil":120,"thema_charm_nonfoil":15,"thema_ferocity_foil":177,"thema_ferocity_nonfoil":22,"thema_foil":826,"thema_grace_foil":152,"thema_grace_nonfoil":19,"thema_mystique_foil":225,"thema_mystique_nonfoil":28,"thema_nonfoil":103,"thema_valor_foil":152,"thema_valor_nonfoil":19,"uuid":"e2Rsg9X1o9","collaborators":[],"circulationTemplates":[{"created_at":"2025-05-27T20:27:36.974+00:00","edition_id":"e2Rsg9X1o9","foil":true,"kind":"FOIL","last_update":"2025-05-27T20:27:36.974+00:00","name":"MRCA U Foil","population":550,"population_operator":"≈","printing":true,"uuid":"cAUDvMk4HC","variants":[]},{"created_at":"2025-05-27T20:27:36.974+00:00","edition_id":"e2Rsg9X1o9","foil":false,"kind":"NONFOIL","last_update":"2025-05-27T20:27:36.974+00:00","name":"MRCA U","population":54200,"population_operator":"≈","printing":true,"uuid":"e7FEx0Jzyn","variants":[]}],"circulations":[],"other_orientations":[],"set":{"created_at":"2025-05-27T20:27:36.974+00:00","id":"a8950b3290","language":"EN","last_update":"2025-05-27T20:27:36.974+00:00","name":"Mercurial Heart Alter Edition","prefix":"MRC Alter","release_date":"2025-05-30T00:00:00"},"effect_html":null}],"rule":[],"slug":"dorumegian-foundry","speed":null,"subtypes":["GUARDIAN","FACTORY"],"types":["DOMAIN"],"uuid":"CzwVavXMQU","effect_html":"<span class=\"effect__block\"><span class=\"effect__bubble\">Class Bonus</span>  This card costs 2 less to activate for each of up to three domains you control.</span><span class=\"effect__label\">On Enter:</span> <span class=\"effect__label\">Summon</span> an Automaton Drone token with a <span class=\"effect__label\">buff</span> counter on it."}