{"classes":["RANGER"],"cost_memory":null,"cost_reserve":3,"created_at":"2024-01-26T12:00:00.000Z","durability":null,"editions":[{"card_id":"gwve1d47o7","collector_number":"061","created_at":"2024-01-26T12:00:00+00:00","effect":null,"effect_raw":null,"flavor":"","illustrator":"坊橋夜泊","image":"/cards/images/lena-dorumegias-herald-alc.jpg","last_update":"2025-01-19T12:25:21.173+00:00","rarity":4,"slug":"lena-dorumegias-herald-alc","thema_charm_foil":292,"thema_charm_nonfoil":55,"thema_ferocity_foil":273,"thema_ferocity_nonfoil":51,"thema_foil":1246,"thema_grace_foil":236,"thema_grace_nonfoil":44,"thema_mystique_foil":204,"thema_mystique_nonfoil":38,"thema_nonfoil":233,"thema_valor_foil":241,"thema_valor_nonfoil":45,"uuid":"cr0ax9z2kc","circulationTemplates":[{"created_at":"2025-01-18T17:40:17.152+00:00","edition_id":"cr0ax9z2kc","foil":false,"kind":"NONFOIL","last_update":"2025-01-18T17:40:17.152+00:00","name":"ALC Super Rare","population":6340,"population_operator":"≈","printing":true,"uuid":"ct3ynbcrae","variants":[]},{"created_at":"2025-01-18T17:40:17.152+00:00","edition_id":"cr0ax9z2kc","foil":true,"kind":"FOIL","last_update":"2025-01-18T17:40:17.152+00:00","name":"ALC Foil Super Rare","population":344,"population_operator":"≈","printing":true,"uuid":"so1p5u153b","variants":[]}],"circulations":[],"set":{"created_at":"2024-01-26T12:00:00+00:00","id":"ul4js2p1ru","language":"EN","last_update":"2025-01-18T17:40:17.152+00:00","name":"Alchemical Revolution","prefix":"ALC","release_date":"2024-01-26T00:00:00"},"effect_html":null}],"effect":"[Class Bonus] **True Sight**\n\n(4), [REST]**:** Look at the top four cards of your deck. You may reveal a Ranger ally card from among them and put it into your hand. Put the rest on the bottom of your deck in any order. This ability costs (2) less to activate as long as CARDNAME is **distant**.","effect_raw":"[Class Bonus] True Sight\n\n(4), REST: Look at the top four cards of your deck. You may reveal a Ranger ally card from among them and put it into your hand. Put the rest on the bottom of your deck in any order. This ability costs (2) less to activate as long as Lena is distant.","element":"NORM","flavor":null,"last_update":"2025-01-20T13:19:43.266Z","legality":null,"level":null,"life":3,"name":"Lena, Dorumegia's Herald","power":1,"referenced_by":[],"references":[],"result_editions":[{"card_id":"gwve1d47o7","collector_number":"061","created_at":"2024-01-26T12:00:00+00:00","effect":null,"effect_raw":null,"flavor":"","illustrator":"坊橋夜泊","image":"/cards/images/lena-dorumegias-herald-alc.jpg","last_update":"2025-01-19T12:25:21.173+00:00","rarity":4,"slug":"lena-dorumegias-herald-alc","thema_charm_foil":292,"thema_charm_nonfoil":55,"thema_ferocity_foil":273,"thema_ferocity_nonfoil":51,"thema_foil":1246,"thema_grace_foil":236,"thema_grace_nonfoil":44,"thema_mystique_foil":204,"thema_mystique_nonfoil":38,"thema_nonfoil":233,"thema_valor_foil":241,"thema_valor_nonfoil":45,"uuid":"cr0ax9z2kc","circulationTemplates":[{"created_at":"2025-01-18T17:40:17.152+00:00","edition_id":"cr0ax9z2kc","foil":false,"kind":"NONFOIL","last_update":"2025-01-18T17:40:17.152+00:00","name":"ALC Super Rare","population":6340,"population_operator":"≈","printing":true,"uuid":"ct3ynbcrae","variants":[]},{"created_at":"2025-01-18T17:40:17.152+00:00","edition_id":"cr0ax9z2kc","foil":true,"kind":"FOIL","last_update":"2025-01-18T17:40:17.152+00:00","name":"ALC Foil Super Rare","population":344,"population_operator":"≈","printing":true,"uuid":"so1p5u153b","variants":[]}],"circulations":[],"set":{"created_at":"2024-01-26T12:00:00+00:00","id":"ul4js2p1ru","language":"EN","last_update":"2025-01-18T17:40:17.152+00:00","name":"Alchemical Revolution","prefix":"ALC","release_date":"2024-01-26T00:00:00"},"effect_html":null}],"rule":[],"slug":"lena-dorumegias-herald","speed":null,"subtypes":["RANGER","HUMAN"],"types":["UNIQUE","ALLY"],"uuid":"gwve1d47o7","effect_html":"<span class=\"effect__block\"><span class=\"effect__bubble\">Class Bonus</span>  <span class=\"effect__label\">True Sight</span></span><span class=\"effect__bubble effect__bubble--yellow ml-2\">4</span>,<span class=\"effect__icon effect__icon--rest\"></span><span class=\"effect__label\">:</span> Look at the top four cards of your deck. You may reveal a Ranger ally card from among them and put it into your hand. Put the rest on the bottom of your deck in any order. This ability costs <span class=\"effect__bubble effect__bubble--yellow ml-2\">2</span>less to activate as long as Lena is <span class=\"effect__label\">distant</span>."}