{"classes":["CLERIC"],"cost_memory":1,"cost_reserve":null,"created_at":"2024-05-17T12:00:00.000Z","durability":null,"editions":[{"card_id":"h9v2214upu","collector_number":"031","configuration":"default","created_at":"2024-05-17T12:00:00+00:00","effect":null,"effect_raw":null,"flavor":null,"illustrator":"木叶","image":"/cards/images/alchemical-scripture-mrc.jpg","last_update":"2025-01-18T17:40:17.152+00:00","orientation":null,"rarity":3,"slug":"alchemical-scripture-mrc","thema_charm_foil":190,"thema_charm_nonfoil":30,"thema_ferocity_foil":177,"thema_ferocity_nonfoil":28,"thema_foil":1060,"thema_grace_foil":184,"thema_grace_nonfoil":29,"thema_mystique_foil":287,"thema_mystique_nonfoil":45,"thema_nonfoil":167,"thema_valor_foil":222,"thema_valor_nonfoil":35,"uuid":"b4qwwvzojo","collaborators":[],"circulationTemplates":[{"created_at":"2025-01-18T17:40:17.152+00:00","edition_id":"b4qwwvzojo","foil":false,"kind":"NONFOIL","last_update":"2025-01-18T17:40:17.152+00:00","name":"MRC Regalia R","population":4611,"population_operator":"≈","printing":true,"uuid":"s278fvscd0","variants":[]},{"created_at":"2025-01-18T17:40:17.152+00:00","edition_id":"b4qwwvzojo","foil":true,"kind":"FOIL","last_update":"2025-01-18T17:40:17.152+00:00","name":"MRC R Foil","population":557,"population_operator":"≈","printing":true,"uuid":"t0eof5o43m","variants":[]}],"circulations":[],"other_orientations":[],"set":{"created_at":"2024-05-17T12:00:00+00:00","id":"urjxrku1pp","language":"EN","last_update":"2025-01-18T17:40:17.152+00:00","name":"Mercurial Heart","prefix":"MRC","release_date":"2024-05-17T00:00:00"},"effect_html":null}],"effect":"At the beginning of your end phase, if you control four or more tokens, draw a card into your memory.","effect_raw":"At the beginning of your end phase, if you control four or more tokens, draw a card into your memory.","element":"NEOS","flavor":"“The theoretics of consumptive alchemy suggest that the energy density of soul matter can be condensed into a hypothetical jewel of limitless potential.”","last_update":"2025-01-22T13:03:38.330Z","legality":null,"level":null,"life":null,"name":"Alchemical Scripture","power":null,"referenced_by":[],"references":[],"result_editions":[{"card_id":"h9v2214upu","collector_number":"031","configuration":"default","created_at":"2024-05-17T12:00:00+00:00","effect":null,"effect_raw":null,"flavor":null,"illustrator":"木叶","image":"/cards/images/alchemical-scripture-mrc.jpg","last_update":"2025-01-18T17:40:17.152+00:00","orientation":null,"rarity":3,"slug":"alchemical-scripture-mrc","thema_charm_foil":190,"thema_charm_nonfoil":30,"thema_ferocity_foil":177,"thema_ferocity_nonfoil":28,"thema_foil":1060,"thema_grace_foil":184,"thema_grace_nonfoil":29,"thema_mystique_foil":287,"thema_mystique_nonfoil":45,"thema_nonfoil":167,"thema_valor_foil":222,"thema_valor_nonfoil":35,"uuid":"b4qwwvzojo","collaborators":[],"circulationTemplates":[{"created_at":"2025-01-18T17:40:17.152+00:00","edition_id":"b4qwwvzojo","foil":false,"kind":"NONFOIL","last_update":"2025-01-18T17:40:17.152+00:00","name":"MRC Regalia R","population":4611,"population_operator":"≈","printing":true,"uuid":"s278fvscd0","variants":[]},{"created_at":"2025-01-18T17:40:17.152+00:00","edition_id":"b4qwwvzojo","foil":true,"kind":"FOIL","last_update":"2025-01-18T17:40:17.152+00:00","name":"MRC R Foil","population":557,"population_operator":"≈","printing":true,"uuid":"t0eof5o43m","variants":[]}],"circulations":[],"other_orientations":[],"set":{"created_at":"2024-05-17T12:00:00+00:00","id":"urjxrku1pp","language":"EN","last_update":"2025-01-18T17:40:17.152+00:00","name":"Mercurial Heart","prefix":"MRC","release_date":"2024-05-17T00:00:00"},"effect_html":null}],"rule":[],"slug":"alchemical-scripture","speed":null,"subtypes":["CLERIC","BOOK"],"types":["REGALIA","ITEM"],"uuid":"h9v2214upu","effect_html":"At the beginning of your end phase, if you control four or more tokens, draw a card into your memory."}