{"classes":["CLERIC"],"cost_memory":null,"cost_reserve":2,"cost":{"type":"reserve","value":"2"},"created_at":"2026-03-28T03:41:55.711Z","durability":null,"editions":[{"card_id":"JFdxtCqdeg","collector_number":"318","configuration":"default","created_at":"2026-03-28T03:41:55.711+00:00","effect":null,"effect_raw":null,"flavor":null,"illustrator":"Dragonart","image":"/cards/images/AaG0TVBZvV.jpg","last_update":"2026-04-01T21:11:30.213+00:00","orientation":null,"rarity":2,"slug":"stellar-bloom-rdo","thema_charm_foil":175,"thema_charm_nonfoil":22,"thema_ferocity_foil":152,"thema_ferocity_nonfoil":19,"thema_foil":893,"thema_grace_foil":191,"thema_grace_nonfoil":24,"thema_mystique_foil":208,"thema_mystique_nonfoil":26,"thema_nonfoil":112,"thema_valor_foil":167,"thema_valor_nonfoil":21,"thema_foil_dynamic":false,"thema_nonfoil_dynamic":false,"uuid":"AaG0TVBZvV","collaborators":[],"circulationTemplates":[{"created_at":"2026-03-28T03:41:55.711+00:00","edition_id":"AaG0TVBZvV","foil":true,"kind":"FOIL","last_update":"2026-03-28T03:41:55.711+00:00","name":"RDO U Foil","population":850,"population_operator":"≈","printing":true,"uuid":"aOxujYElOI","variants":[{"uuid":"EKByi12icF","edition_id":"AaG0TVBZvV","description":"Aurora Curio Foil","image":"/cards/images/AaG0TVBZvV.jpg","population_operator":"=","population":100,"printing":false,"kind":"FOIL","created_at":"2026-03-28T03:41:55.711+00:00","last_update":"2026-03-28T03:41:55.711+00:00"}]},{"created_at":"2026-03-28T03:41:55.711+00:00","edition_id":"AaG0TVBZvV","foil":false,"kind":"NONFOIL","last_update":"2026-03-28T03:41:55.711+00:00","name":"RDO U NF","population":67000,"population_operator":"≈","printing":true,"uuid":"UI1C2QfYBv","variants":[]}],"circulations":[],"other_orientations":[],"set":{"created_at":"2026-03-28T03:41:55.711+00:00","id":"90ec0d2ed5","language":"EN","last_update":"2026-03-28T03:41:55.711+00:00","name":"Radiant Origins","prefix":"RDO","release_date":"2026-04-03T00:00:00"},"effect_html":null},{"card_id":"JFdxtCqdeg","collector_number":"196","configuration":"default","created_at":"2026-03-28T03:41:55.711+00:00","effect":null,"effect_raw":null,"flavor":null,"illustrator":"Dragonart\n","image":"/cards/images/ZBBhpyNlEc.jpg","last_update":"2026-04-01T21:11:30.213+00:00","orientation":null,"rarity":2,"slug":"stellar-bloom-rdopd","thema_charm_foil":null,"thema_charm_nonfoil":22,"thema_ferocity_foil":null,"thema_ferocity_nonfoil":19,"thema_foil":null,"thema_grace_foil":null,"thema_grace_nonfoil":22,"thema_mystique_foil":null,"thema_mystique_nonfoil":23,"thema_nonfoil":106,"thema_valor_foil":null,"thema_valor_nonfoil":20,"thema_foil_dynamic":false,"thema_nonfoil_dynamic":false,"uuid":"ZBBhpyNlEc","collaborators":[],"circulationTemplates":[],"circulations":[{"created_at":"2026-03-28T03:41:55.711+00:00","edition_id":"ZBBhpyNlEc","foil":false,"kind":"NONFOIL","last_update":"2026-03-28T03:41:55.711+00:00","population":8000,"population_operator":"≈","printing":true,"uuid":"AmgvHVGJOw","variants":[]}],"other_orientations":[],"set":{"created_at":"2026-03-28T03:41:55.711+00:00","id":"f2c0af1699","language":"EN","last_update":"2026-03-28T03:41:55.711+00:00","name":"Radiant Origins Pantheon Decks","prefix":"RDOPD","release_date":"2026-04-03T00:00:00"},"effect_html":null}],"effect":"[Class Bonus] **Starcalling —** (2) *(As you're looking at this card while **glimpsing**, you may activate it by paying this cost. If you do, put all other cards you're looking at on the bottom of your deck in any order.)*\n\n**Gather** four times.","effect_raw":"[Class Bonus] Starcalling — (2) (As you're looking at this card while glimpsing, you may activate it by paying this cost. If you do, put all other cards you're looking at on the bottom of your deck in any order.)\n\nGather four times.","element":"ASTRA","elements":["ASTRA"],"flavor":null,"last_update":"2026-04-02T19:55:28.177Z","legality":null,"level":null,"life":null,"name":"Stellar Bloom","power":null,"referenced_by":[],"references":[{"kind":"SUMMON","name":"Blightroot","slug":"blightroot","direction":"TO"},{"kind":"SUMMON","name":"Manaroot","slug":"manaroot","direction":"TO"},{"kind":"SUMMON","name":"Silvershine","slug":"silvershine","direction":"TO"},{"kind":"SUMMON","name":"Fraysia","slug":"fraysia","direction":"TO"},{"kind":"SUMMON","name":"Razorvine","slug":"razorvine","direction":"TO"},{"kind":"SUMMON","name":"Springleaf","slug":"springleaf","direction":"TO"}],"result_editions":[{"card_id":"JFdxtCqdeg","collector_number":"196","configuration":"default","created_at":"2026-03-28T03:41:55.711+00:00","effect":null,"effect_raw":null,"flavor":null,"illustrator":"Dragonart\n","image":"/cards/images/ZBBhpyNlEc.jpg","last_update":"2026-04-01T21:11:30.213+00:00","orientation":null,"rarity":2,"slug":"stellar-bloom-rdopd","thema_charm_foil":null,"thema_charm_nonfoil":22,"thema_ferocity_foil":null,"thema_ferocity_nonfoil":19,"thema_foil":null,"thema_grace_foil":null,"thema_grace_nonfoil":22,"thema_mystique_foil":null,"thema_mystique_nonfoil":23,"thema_nonfoil":106,"thema_valor_foil":null,"thema_valor_nonfoil":20,"thema_foil_dynamic":false,"thema_nonfoil_dynamic":false,"uuid":"ZBBhpyNlEc","collaborators":[],"circulationTemplates":[],"circulations":[{"created_at":"2026-03-28T03:41:55.711+00:00","edition_id":"ZBBhpyNlEc","foil":false,"kind":"NONFOIL","last_update":"2026-03-28T03:41:55.711+00:00","population":8000,"population_operator":"≈","printing":true,"uuid":"AmgvHVGJOw","variants":[]}],"other_orientations":[],"set":{"created_at":"2026-03-28T03:41:55.711+00:00","id":"f2c0af1699","language":"EN","last_update":"2026-03-28T03:41:55.711+00:00","name":"Radiant Origins Pantheon Decks","prefix":"RDOPD","release_date":"2026-04-03T00:00:00"},"effect_html":null}],"rule":[],"slug":"stellar-bloom","speed":false,"subtypes":["CLERIC","SKILL"],"types":["ACTION"],"uuid":"JFdxtCqdeg","effect_html":"<span class=\"effect__block\"><span class=\"effect__bubble\">Class Bonus</span>  <span class=\"effect__label\">Starcalling —</span> <span class=\"effect__bubble effect__bubble--yellow ml-2\">2</span><span class=\"effect__reminder\">(As you're looking at this card while <span class=\"effect__label\">glimpsing</span>, you may activate it by paying this cost. If you do, put all other cards you're looking at on the bottom of your deck in any order.)</span></span><span class=\"effect__label\">Gather</span> four times."}