{"classes":["CLERIC"],"cost_memory":null,"cost_reserve":3,"created_at":"2025-11-24T09:52:36.684Z","durability":null,"editions":[{"card_id":"tJAIMX3C4R","collector_number":"120","configuration":"default","created_at":"2025-11-24T09:52:36.684+00:00","effect":null,"effect_raw":null,"flavor":"\"Such a trial, dear Sir, with no jury or judge, would be wasting our breath.\"","illustrator":"Primea Studio","image":"/cards/images/5K9g445aO9.jpg","last_update":"2025-11-24T16:18:03.555+00:00","orientation":null,"rarity":2,"slug":"misty-whispertail-ptm","thema_charm_foil":181,"thema_charm_nonfoil":23,"thema_ferocity_foil":160,"thema_ferocity_nonfoil":20,"thema_foil":893,"thema_grace_foil":176,"thema_grace_nonfoil":22,"thema_mystique_foil":200,"thema_mystique_nonfoil":25,"thema_nonfoil":112,"thema_valor_foil":176,"thema_valor_nonfoil":22,"uuid":"5K9g445aO9","collaborators":[],"circulationTemplates":[{"created_at":"2025-11-24T09:52:36.684+00:00","edition_id":"5K9g445aO9","foil":true,"kind":"FOIL","last_update":"2025-11-24T09:52:36.684+00:00","name":"PTM U Foil","population":1100,"population_operator":"≈","printing":true,"uuid":"ELqen2ZIse","variants":[{"uuid":"0DhTXvSnpk","edition_id":"5K9g445aO9","description":"Fractured Curio Foil","image":"/cards/images/5K9g445aO9.jpg","population_operator":"≈","population":100,"printing":false,"kind":"FOIL","created_at":"2025-11-24T09:52:36.684+00:00","last_update":"2025-11-24T09:52:36.684+00:00"}]},{"created_at":"2025-11-24T09:52:36.684+00:00","edition_id":"5K9g445aO9","foil":false,"kind":"NONFOIL","last_update":"2025-11-24T09:52:36.684+00:00","name":"PTM U Nonfoil","population":58500,"population_operator":"≈","printing":true,"uuid":"ZNpO0gSlgs","variants":[]}],"circulations":[],"other_orientations":[],"set":{"created_at":"2025-11-24T09:52:36.684+00:00","id":"c15ff15598","language":"EN","last_update":"2025-11-24T09:52:36.684+00:00","name":"Phantom Monarchs","prefix":"PTM","release_date":"2025-12-05T00:00:00"},"effect_html":null}],"effect":"**Sacrifice CARDNAME:** If CARDNAME was not **ephemeral**, draw a card into your memory. Otherwise, **recover 3**.","effect_raw":"Sacrifice Misty Whispertail: If Misty Whispertail was not ephemeral, draw a card into your memory. Otherwise, recover 3.","element":"WATER","elements":["WATER"],"flavor":"\"Such a trial, dear Sir, with no jury or judge, would be wasting our breath.\"","last_update":"2025-12-05T08:15:58.313Z","legality":null,"level":null,"life":3,"name":"Misty Whispertail","power":1,"referenced_by":[],"references":[],"result_editions":[{"card_id":"tJAIMX3C4R","collector_number":"120","configuration":"default","created_at":"2025-11-24T09:52:36.684+00:00","effect":null,"effect_raw":null,"flavor":"\"Such a trial, dear Sir, with no jury or judge, would be wasting our breath.\"","illustrator":"Primea Studio","image":"/cards/images/5K9g445aO9.jpg","last_update":"2025-11-24T16:18:03.555+00:00","orientation":null,"rarity":2,"slug":"misty-whispertail-ptm","thema_charm_foil":181,"thema_charm_nonfoil":23,"thema_ferocity_foil":160,"thema_ferocity_nonfoil":20,"thema_foil":893,"thema_grace_foil":176,"thema_grace_nonfoil":22,"thema_mystique_foil":200,"thema_mystique_nonfoil":25,"thema_nonfoil":112,"thema_valor_foil":176,"thema_valor_nonfoil":22,"uuid":"5K9g445aO9","collaborators":[],"circulationTemplates":[{"created_at":"2025-11-24T09:52:36.684+00:00","edition_id":"5K9g445aO9","foil":true,"kind":"FOIL","last_update":"2025-11-24T09:52:36.684+00:00","name":"PTM U Foil","population":1100,"population_operator":"≈","printing":true,"uuid":"ELqen2ZIse","variants":[{"uuid":"0DhTXvSnpk","edition_id":"5K9g445aO9","description":"Fractured Curio Foil","image":"/cards/images/5K9g445aO9.jpg","population_operator":"≈","population":100,"printing":false,"kind":"FOIL","created_at":"2025-11-24T09:52:36.684+00:00","last_update":"2025-11-24T09:52:36.684+00:00"}]},{"created_at":"2025-11-24T09:52:36.684+00:00","edition_id":"5K9g445aO9","foil":false,"kind":"NONFOIL","last_update":"2025-11-24T09:52:36.684+00:00","name":"PTM U Nonfoil","population":58500,"population_operator":"≈","printing":true,"uuid":"ZNpO0gSlgs","variants":[]}],"circulations":[],"other_orientations":[],"set":{"created_at":"2025-11-24T09:52:36.684+00:00","id":"c15ff15598","language":"EN","last_update":"2025-11-24T09:52:36.684+00:00","name":"Phantom Monarchs","prefix":"PTM","release_date":"2025-12-05T00:00:00"},"effect_html":null}],"rule":[],"slug":"misty-whispertail","speed":null,"subtypes":["CLERIC","SPECTER","ANIMAL","MOUSE"],"types":["ALLY"],"uuid":"tJAIMX3C4R","effect_html":"<span class=\"effect__label\">Sacrifice Misty Whispertail:</span> If Misty Whispertail was not <span class=\"effect__label\">ephemeral</span>, draw a card into your memory. Otherwise, <span class=\"effect__label\">recover 3</span>."}