{"uuid":"WI2owxIw0z","types":["CHAMPION"],"classes":["WARRIOR"],"subtypes":["WARRIOR","HUMAN"],"element":"NORM","name":"Mordred, Flawless Blade","slug":"mordred-flawless-blade","effect":"Attack cards in your graveyard have <span class=\"effect__label\">floating memory</span>. <span class=\"effect__reminder\">(While paying for a memory cost, you may banish a card with <span class=\"effect__label\">floating memory</span> from your graveyard to pay for 1 of that cost.)</span>","effect_raw":"Attack cards in your graveyard have floating memory. (While paying for a memory cost, you may banish a card with floating memory from your graveyard to pay for 1 of that cost.)","rule":[{"title":"","date_added":"2022-12-27","description":"Multiple instances of floating memory on the same card are redundant. Any instances beyond the first are ignored."}],"flavor":"\"Do try to keep up, won't you?\"","cost_memory":2,"cost_reserve":null,"level":2,"power":null,"life":24,"durability":null,"speed":null,"related_ids":null,"last_update":"2022-12-26T06:00:00.000Z","result_editions":[{"uuid":"HLOHk9mGT9","card_id":"WI2owxIw0z","collector_number":"018","slug":"mordred-flawless-blade-doa1e","illustrator":"Hanh Chu","rarity":1,"effect":null,"flavor":null,"circulations":[],"circulationTemplates":[{"uuid":"Ew6jY9blQq","name":"DOA1e Champions 2","foil":false,"printing":false,"population_operator":"≈","population":25000}],"set":{"name":"Dawn of Ashes First Edition","prefix":"DOA 1st","language":"EN"}}],"editions":[{"uuid":"HLOHk9mGT9","card_id":"WI2owxIw0z","collector_number":"018","slug":"mordred-flawless-blade-doa1e","illustrator":"Hanh Chu","rarity":1,"effect":null,"flavor":null,"last_update":"2022-12-26T06:00:00.000Z","circulations":[],"circulationTemplates":[{"uuid":"Ew6jY9blQq","name":"DOA1e Champions 2","foil":false,"printing":false,"population_operator":"≈","population":25000}],"set":{"name":"Dawn of Ashes First Edition","prefix":"DOA 1st","language":"EN","last_update":"2022-12-26T06:00:00.000Z"}}]}